outline/__init__.py
outline/_base_client.py
outline/_client.py
outline/_compat.py
outline/_constants.py
outline/_exceptions.py
outline/_files.py
outline/_models.py
outline/_qs.py
outline/_resource.py
outline/_response.py
outline/_streaming.py
outline/_types.py
outline/_version.py
outline/py.typed
outline/_utils/__init__.py
outline/_utils/_logs.py
outline/_utils/_proxy.py
outline/_utils/_reflection.py
outline/_utils/_streams.py
outline/_utils/_sync.py
outline/_utils/_transform.py
outline/_utils/_typing.py
outline/_utils/_utils.py
outline/lib/.keep
outline/resources/__init__.py
outline/resources/attachments.py
outline/resources/auth.py
outline/resources/comments.py
outline/resources/documents.py
outline/resources/events.py
outline/resources/file_operations.py
outline/resources/groups.py
outline/resources/collections/__init__.py
outline/resources/collections/collections.py
outline/resources/collections/group_memberships.py
outline/resources/collections/memberships.py
outline/types/__init__.py
outline/types/attachment_create_params.py
outline/types/attachment_create_response.py
outline/types/attachment_delete_params.py
outline/types/attachment_delete_response.py
outline/types/attachment_redirect_params.py
outline/types/auth.py
outline/types/auth_config_response.py
outline/types/auth_info_response.py
outline/types/collection.py
outline/types/collection_add_group_params.py
outline/types/collection_add_group_response.py
outline/types/collection_add_user_params.py
outline/types/collection_add_user_response.py
outline/types/collection_create_params.py
outline/types/collection_create_response.py
outline/types/collection_delete_params.py
outline/types/collection_delete_response.py
outline/types/collection_documents_params.py
outline/types/collection_documents_response.py
outline/types/collection_export_all_params.py
outline/types/collection_export_all_response.py
outline/types/collection_export_params.py
outline/types/collection_export_response.py
outline_python_api-0.4.0a0.dist-info/METADATA
outline_python_api-0.4.0a0.dist-info/WHEEL
outline_python_api-0.4.0a0.dist-info/licenses/LICENSE
outline_python_api-0.4.0a0.dist-info/RECORD
